{
	"type": "avatar",
	"polyNode": {
		"locked": false
	},
	"nodes": {
		"box1": {
			"type": "box"
		},
		"material1": {
			"type": "material",
			"params": {
				"material": "../MAT/meshStandard1"
			},
			"inputs": ["box1"]
		},
		"subnetOutput1": {
			"type": "subnetOutput",
			"inputs": ["transform1"],
			"flags": {
				"display": true
			}
		},
		"transform1": {
			"type": "transform",
			"params": {
				"t": [0, 2, 0]
			},
			"inputs": ["material1"]
		}
	},
	"flags": {
		"display": true
	}
}
